{
  "console.autocomplete.addMethodMetaText": "method",
  "console.consoleDisplayName": "Console",
  "console.consoleMenu.copyAsCurlFailedMessage": "Could not copy request as cURL",
  "console.consoleMenu.copyAsCurlMessage": "Request copied as cURL",
  "console.devToolsDescription": "Skip cURL and use a JSON interface to work with your data in Console.",
  "console.devToolsTitle": "Interact with the Elasticsearch API",
  "console.exampleOutputTextarea": "Dev Tools Console editor example",
  "console.helpPage.keyboardCommands.autoIndentDescription": "Auto indent current request",
  "console.helpPage.keyboardCommands.closeAutoCompleteMenuDescription": "Close auto-complete menu",
  "console.helpPage.keyboardCommands.collapseAllScopesDescription": "Collapse all scopes but the current one. Expand by adding a shift.",
  "console.helpPage.keyboardCommands.collapseExpandCurrentScopeDescription": "Collapse/expand current scope.",
  "console.helpPage.keyboardCommands.jumpToPreviousNextRequestDescription": "Jump to the previous/next request start or end.",
  "console.helpPage.keyboardCommands.openAutoCompleteDescription": "Open Auto complete (even if not typing)",
  "console.helpPage.keyboardCommands.openDocumentationDescription": "Open documentation for current request",
  "console.helpPage.keyboardCommands.selectCurrentlySelectedInAutoCompleteMenuDescription": "Select the currently selected or the top most term in auto-complete menu",
  "console.helpPage.keyboardCommands.submitRequestDescription": "Submit request",
  "console.helpPage.keyboardCommands.switchFocusToAutoCompleteMenuDescription": "Switch focus to auto-complete menu. Use arrows to further select a term",
  "console.helpPage.keyboardCommandsTitle": "Keyboard commands",
  "console.helpPage.pageTitle": "Help",
  "console.helpPage.requestFormatDescription": "You can type one or more requests in the white editor. Console understands requests in a compact format:",
  "console.helpPage.requestFormatTitle": "Request format",
  "console.historyPage.applyHistoryButtonLabel": "Apply",
  "console.historyPage.clearHistoryButtonLabel": "Clear",
  "console.historyPage.closehistoryButtonLabel": "Close",
  "console.historyPage.itemOfRequestListAriaLabel": "Request: {historyItem}",
  "console.historyPage.noHistoryTextMessage": "No history available",
  "console.historyPage.pageTitle": "History",
  "console.historyPage.requestListAriaLabel": "History of sent requests",
  "console.inputTextarea": "Dev Tools Console",
  "console.loadingError.buttonLabel": "Reload Console",
  "console.loadingError.message": "Try reloading to get the latest data.",
  "console.loadingError.title": "Cannot load Console",
  "console.notification.error.couldNotSaveRequestTitle": "Could not save request to Console history.",
  "console.notification.error.historyQuotaReachedMessage": "Request history is full. Clear the Console history to save new requests.",
  "console.notification.error.noRequestSelectedTitle": "No request selected. Select a request by placing the cursor inside it.",
  "console.notification.error.unknownErrorTitle": "Unknown Request Error",
  "console.outputTextarea": "Dev Tools Console output",
  "console.pageHeading": "Console",
  "console.requestInProgressBadgeText": "Request in progress",
  "console.requestOptions.autoIndentButtonLabel": "Auto indent",
  "console.requestOptions.copyAsUrlButtonLabel": "Copy as cURL",
  "console.requestOptions.openDocumentationButtonLabel": "Open documentation",
  "console.requestOptionsButtonAriaLabel": "Request options",
  "console.requestTimeElapasedBadgeTooltipContent": "Time Elapsed",
  "console.sendRequestButtonTooltip": "Click to send request",
  "console.settingsPage.autocompleteLabel": "Autocomplete",
  "console.settingsPage.cancelButtonLabel": "Cancelar",
  "console.settingsPage.fieldsLabelText": "Fields",
  "console.settingsPage.fontSizeLabel": "Font Size",
  "console.settingsPage.indicesAndAliasesLabelText": "Indices & Aliases",
  "console.settingsPage.jsonSyntaxLabel": "JSON syntax",
  "console.settingsPage.pageTitle": "Console Settings",
  "console.settingsPage.pollingLabelText": "Automatically refresh autocomplete suggestions",
  "console.settingsPage.refreshButtonLabel": "Refresh autocomplete suggestions",
  "console.settingsPage.refreshingDataDescription": "Console refreshes autocomplete suggestions by querying Elasticsearch. Automatic refreshes may be an issue if you have a large cluster or if you have network limitations.",
  "console.settingsPage.refreshingDataLabel": "Refreshing autocomplete suggestions",
  "console.settingsPage.saveButtonLabel": "Salvar",
  "console.settingsPage.templatesLabelText": "Templates",
  "console.settingsPage.tripleQuotesMessage": "Use triple quotes in output pane",
  "console.settingsPage.wrapLongLinesLabelText": "Wrap long lines",
  "console.topNav.helpTabDescription": "Help",
  "console.topNav.helpTabLabel": "Help",
  "console.topNav.historyTabDescription": "History",
  "console.topNav.historyTabLabel": "History",
  "console.topNav.settingsTabDescription": "Settings",
  "console.topNav.settingsTabLabel": "Settings",
  "console.welcomePage.closeButtonLabel": "Dismiss",
  "console.welcomePage.pageTitle": "Welcome to Console",
  "console.welcomePage.quickIntroDescription": "The Console UI is split into two panes: an editor pane (left) and a response pane (right). Use the editor to type requests and submit them to Elasticsearch. The results will be displayed in the response pane on the right side.",
  "console.welcomePage.quickIntroTitle": "Quick intro to the UI",
  "console.welcomePage.quickTips.cUrlFormatForRequestsDescription": "You can paste requests in cURL format and they will be translated to the Console syntax.",
  "console.welcomePage.quickTips.keyboardShortcutsDescription": "Study the keyboard shortcuts under the Help button. Good stuff in there!",
  "console.welcomePage.quickTips.resizeEditorDescription": "You can resize the editor and output panes by dragging the separator between them.",
  "console.welcomePage.quickTips.submitRequestDescription": "Submit requests to ES using the green triangle button.",
  "console.welcomePage.quickTips.useWrenchMenuDescription": "Use the wrench menu for other useful things.",
  "console.welcomePage.quickTipsTitle": "A few quick tips, while I have your attention",
  "console.welcomePage.supportedRequestFormatDescription": "While typing a request, Console will make suggestions which you can then accept by hitting Enter/Tab. These suggestions are made based on the request structure as well as your indices and types.",
  "console.welcomePage.supportedRequestFormatTitle": "Console understands requests in a compact format, similar to cURL:"
}